pyprogs/__init.py__
pyprogs/a.py
pyprogs/main.py
pyprogs-1.0.0.dist-info/METADATA
pyprogs-1.0.0.dist-info/WHEEL
pyprogs-1.0.0.dist-info/entry_points.txt
pyprogs-1.0.0.dist-info/RECORD
