Metadata-Version: 2.1
Name: pyprogs
Version: 1.0.0
Summary: pyprogs
Author: Ananth G S
Author-email: ananth.gouri@gmail.com
Requires-Python: >=3.9,<4.0
Classifier: Programming Language :: Python :: 3
Classifier: Programming Language :: Python :: 3.9
Classifier: Programming Language :: Python :: 3.10
Classifier: Programming Language :: Python :: 3.11
Classifier: Programming Language :: Python :: 3.12
